[
  {
    "id": "math_001",
    "question": "What is the value of π (pi) to two decimal places?",
    "options": [
      "3.14",
      "3.15",
      "3.16",
      "3.17"
    ],
    "correctAnswerIndex": 0,
    "explanation": "π (pi) is approximately 3.14159...",
    "subject": "mathematics",
    "topic": "algebra",
    "difficultyLevel": "EASY"
  },
  {
    "id": "math_002",
    "question": "Solve for x: 2x + 5 = 13",
    "options": [
      "x = 4",
      "x = 5",
      "x = 6",
      "x = 7"
    ],
    "correctAnswerIndex": 0,
    "explanation": "2x + 5 = 13\n2x = 8\nx = 4",
    "subject": "mathematics",
    "topic": "algebra",
    "difficultyLevel": "EASY"
  },
  {
    "id": "math_003",
    "question": "What is the area of a circle with radius 5 units?",
    "options": [
      "25π",
      "50π",
      "75π",
      "100π"
    ],
    "correctAnswerIndex": 0,
    "explanation": "Area = πr² = π(5)² = 25π",
    "subject": "mathematics",
    "topic": "geometry",
    "difficultyLevel": "MEDIUM"
  },
  {
    "id": "math_004",
    "question": "What is the derivative of x²?",
    "options": [
      "x",
      "2x",
      "x²",
      "2x²"
    ],
    "correctAnswerIndex": 1,
    "explanation": "The derivative of x² is 2x using the power rule",
    "subject": "mathematics",
    "topic": "calculus",
    "difficultyLevel": "MEDIUM"
  },
  {
    "id": "math_005",
    "question": "What is the value of sin(30°)?",
    "options": [
      "0.5",
      "0.707",
      "0.866",
      "1.0"
    ],
    "correctAnswerIndex": 0,
    "explanation": "sin(30°) = 0.5",
    "subject": "mathematics",
    "topic": "trigonometry",
    "difficultyLevel": "EASY"
  }
] 